zero_migrations/__init__.py
zero_migrations/apps.py
zero_migrations/constants.py
zero_migrations/exceptions.py
zero_migrations/management/__init__.py
zero_migrations/management/commands/__init__.py
zero_migrations/management/commands/zeromigrations.py
zero_migrations/utils/__init__.py
zero_migrations/utils/backup.py
zero_migrations/utils/restore.py
django_zeromigrations-0.3.1.dist-info/LICENSE
django_zeromigrations-0.3.1.dist-info/METADATA
django_zeromigrations-0.3.1.dist-info/WHEEL
django_zeromigrations-0.3.1.dist-info/top_level.txt
django_zeromigrations-0.3.1.dist-info/RECORD
