Metadata-Version: 2.1
Name: django-zeromigrations
Version: 0.3.1
Summary: Django reset migrations with `zeromigrations` command with backup feature
Home-page: https://github.com/aminiun/django-zeromigrations
Author: Amin Aminian
Author-email: a.aminian321@gmail.com
License: BSD-3-Clause
Classifier: Environment :: Web Environment
Classifier: Intended Audience :: Developers
Classifier: License :: OSI Approved :: BSD License
Classifier: Operating System :: OS Independent
Classifier: Framework :: Django
Classifier: Programming Language :: Python :: 3 :: Only
Classifier: Topic :: Software Development :: Libraries :: Application Frameworks
Classifier: Topic :: Software Development :: Libraries :: Python Modules
Requires-Python: >=3.6
License-File: LICENSE
Requires-Dist: Django (>=2.2)
